efin/__init__.py
efin/caching.py
efin/cli.py
efin/forecast.py
efin/forecast_arima_grid.py
efin/forecast_prophet.py
efin/portfolio.py
efin/risk.py
efin/tesst.py
efin/triangle.py
efin/valuation.py
efin/value.py
efin/visualization.py
efin-2.4.0.dist-info/METADATA
efin-2.4.0.dist-info/WHEEL
efin-2.4.0.dist-info/top_level.txt
efin-2.4.0.dist-info/RECORD
