Metadata-Version: 2.4
Name: efin
Version: 2.4.0
Summary: A comprehensive financial analysis and forecasting library
Home-page: https://github.com/ebeirne/efin
Author: Ethan Beirne
Author-email: ethan.g.beirne@gmail.com
Classifier: Programming Language :: Python :: 3
Classifier: License :: OSI Approved :: MIT License
Classifier: Operating System :: OS Independent
Requires-Python: >=3.6
Requires-Dist: yfinance
Requires-Dist: statsmodels
Requires-Dist: prophet
Requires-Dist: click
Requires-Dist: requests_cache
Requires-Dist: matplotlib
Requires-Dist: numpy
Requires-Dist: pandas
Requires-Dist: scikit-learn
Dynamic: author
Dynamic: author-email
Dynamic: classifier
Dynamic: description
Dynamic: description-content-type
Dynamic: home-page
Dynamic: requires-dist
Dynamic: requires-python
Dynamic: summary
